act/__init__.py
act/_appbase.py
act/_log.py
act/_msgpack.py
act/_resources.py
act/_zkit.py
cobe_act-1.7.0.dist-info/DESCRIPTION.rst
cobe_act-1.7.0.dist-info/METADATA
cobe_act-1.7.0.dist-info/RECORD
cobe_act-1.7.0.dist-info/WHEEL
cobe_act-1.7.0.dist-info/metadata.json
cobe_act-1.7.0.dist-info/top_level.txt
