Metadata-Version: 2.0
Name: cobe-act
Version: 1.7.0
Summary: A collection of common tools for cobe.io.
Home-page: http://bitbucket.org/cobeio/act
Author: cobe.io
Author-email: info@cobe.io
License: LGPLv3
Platform: UNKNOWN
Classifier: Development Status :: 4 - Beta
Classifier: License :: Other/Proprietary License
Classifier: Intended Audience :: Developers
Classifier: License :: OSI Approved :: GNU Lesser General Public License v3 (LGPLv3)
Classifier: Topic :: Software Development :: Libraries
Classifier: Programming Language :: Python :: 3 :: Only
Classifier: Programming Language :: Python :: 3.4
Classifier: Programming Language :: Python :: 3.5
Requires-Dist: Logbook
Requires-Dist: apipkg
Requires-Dist: dnspython
Requires-Dist: msgpack-python
Requires-Dist: pyzmq
Requires-Dist: setuptools
